fidmaa_simple_viewer/__init__.py
fidmaa_simple_viewer/core.py
fidmaa_simple_viewer-0.1.0.dist-info/LICENSE
fidmaa_simple_viewer-0.1.0.dist-info/METADATA
fidmaa_simple_viewer-0.1.0.dist-info/WHEEL
fidmaa_simple_viewer-0.1.0.dist-info/entry_points.txt
fidmaa_simple_viewer-0.1.0.dist-info/RECORD
