Metadata-Version: 2.1
Name: fidmaa-simple-viewer
Version: 0.1.0
Summary: Simple viewer for depth-mapped images
License: MIT
Author: Michał Pasternak
Author-email: michal.dtz@gmail.com
Requires-Python: >=3.12,<4.0
Classifier: License :: OSI Approved :: MIT License
Classifier: Programming Language :: Python :: 3
Classifier: Programming Language :: Python :: 3.12
Requires-Dist: click (>=8.1.7,<9.0.0)
Requires-Dist: numpy (>=1.26.4,<2.0.0)
Requires-Dist: opencv-python (>=4.9.0.80,<5.0.0.0)
Requires-Dist: portrait-analyser (>=0.1.2,<0.2.0)
Requires-Dist: pyvista (>=0.43.4,<0.44.0)
Requires-Dist: tqdm (>=4.66.2,<5.0.0)
